skill_device_controls/LICENSE.md
skill_device_controls/README.md
skill_device_controls/__init__.py
skill_device_controls/skill.json
skill_device_controls/version.py
skill_device_controls/locale/en-us/dialog/action_not_confirmed.dialog
skill_device_controls/locale/en-us/dialog/already_requiring.dialog
skill_device_controls/locale/en-us/dialog/already_skipping.dialog
skill_device_controls/locale/en-us/dialog/ask_disable_ww.dialog
skill_device_controls/locale/en-us/dialog/ask_exit_shutdown.dialog
skill_device_controls/locale/en-us/dialog/ask_start_requiring.dialog
skill_device_controls/locale/en-us/dialog/ask_start_skipping.dialog
skill_device_controls/locale/en-us/dialog/confirm_brain_disabled.dialog
skill_device_controls/locale/en-us/dialog/confirm_brain_enabled.dialog
skill_device_controls/locale/en-us/dialog/confirm_cancel.dialog
skill_device_controls/locale/en-us/dialog/confirm_exiting.dialog
skill_device_controls/locale/en-us/dialog/confirm_listening_disabled.dialog
skill_device_controls/locale/en-us/dialog/confirm_listening_enabled.dialog
skill_device_controls/locale/en-us/dialog/confirm_require_ww.dialog
skill_device_controls/locale/en-us/dialog/confirm_restarting.dialog
skill_device_controls/locale/en-us/dialog/confirm_shutdown.dialog
skill_device_controls/locale/en-us/dialog/confirm_skip_ww.dialog
skill_device_controls/locale/en-us/dialog/confirm_ww_changed.dialog
skill_device_controls/locale/en-us/dialog/confirm_ww_changing.dialog
skill_device_controls/locale/en-us/dialog/confirm_ww_disabled.dialog
skill_device_controls/locale/en-us/dialog/error_invalid_ww_requested.dialog
skill_device_controls/locale/en-us/dialog/error_no_ww_api.dialog
skill_device_controls/locale/en-us/dialog/error_no_ww_heard.dialog
skill_device_controls/locale/en-us/dialog/error_ww_already_enabled.dialog
skill_device_controls/locale/en-us/dialog/error_ww_change_failed.dialog
skill_device_controls/locale/en-us/dialog/not_doing_anything.dialog
skill_device_controls/neon_skill_device_controls.egg-info/PKG-INFO
skill_device_controls/neon_skill_device_controls.egg-info/SOURCES.txt
skill_device_controls/neon_skill_device_controls.egg-info/dependency_links.txt
skill_device_controls/neon_skill_device_controls.egg-info/entry_points.txt
skill_device_controls/neon_skill_device_controls.egg-info/requires.txt
skill_device_controls/neon_skill_device_controls.egg-info/top_level.txt
neon_skill_device_controls-1.2.0.dist-info/LICENSE.md
neon_skill_device_controls-1.2.0.dist-info/METADATA
neon_skill_device_controls-1.2.0.dist-info/WHEEL
neon_skill_device_controls-1.2.0.dist-info/entry_points.txt
neon_skill_device_controls-1.2.0.dist-info/top_level.txt
neon_skill_device_controls-1.2.0.dist-info/RECORD
